setup.py
WindowsXP/__init__.py
WindowsXP.egg-info/PKG-INFO
WindowsXP.egg-info/SOURCES.txt
WindowsXP.egg-info/dependency_links.txt
WindowsXP.egg-info/top_level.txt